pdfoutliner/__init__.py
pdfoutliner/__main__.py
pdfoutliner-0.0.4.dist-info/LICENSE
pdfoutliner-0.0.4.dist-info/METADATA
pdfoutliner-0.0.4.dist-info/WHEEL
pdfoutliner-0.0.4.dist-info/entry_points.txt
pdfoutliner-0.0.4.dist-info/top_level.txt
pdfoutliner-0.0.4.dist-info/RECORD
