Metadata-Version: 2.1
Name: pdfoutliner
Version: 0.0.4
Summary: Command line interface for generating pdftk-style bookmark files in a user-friendly way, and (optionally) outputs a PDF file with the specified outline.
Home-page: https://github.com/pnlng/pdfoutliner
Author: pnlng
License: UNKNOWN
Platform: UNKNOWN
Classifier: Programming Language :: Python :: 3
Classifier: License :: OSI Approved :: MIT License
Classifier: Operating System :: OS Independent
Requires-Python: >=3.5
